rss/__init__.py
rss/auth.py
rss/schedular.py
rss/tracker.py
rss/utils.py
rss/apps/__init__.py
rss/apps/bark.py
rss/apps/device.py
rss/apps/dropbox_monitor.py
rss/apps/freeapp.py
rss/apps/huggingface.py
rss/apps/leiphone.py
rss/apps/mediaporter.py
rss/apps/meituan.py
rss/apps/openai.py
rss/apps/rsshub.py
rss/apps/rust.py
rss/apps/tensorflow.py
rss/apps/data/__init__.py
rss/base/__init__.py
rss/base/anynews.py
rss/base/bm25.py
rss/base/pipeline.py
rss/base/sif.py
rss/base/todb.py
rss/base/types.py
rss/base/urlparser.py
rss/base/wechat_public.py
rss/base/wechat_rss.py
rss/core/__init__.py
rss/core/tg.py
rss/core/toolkits.py
rss/core/web.py
rss/data/__init__.py
rss/data/db.py
rss/data/rust_doc_chapters.py
rsspy-0.2.5.dist-info/METADATA
rsspy-0.2.5.dist-info/WHEEL
rsspy-0.2.5.dist-info/entry_points.txt
rsspy-0.2.5.dist-info/top_level.txt
rsspy-0.2.5.dist-info/RECORD
