Metadata-Version: 2.1
Name: rsspy
Version: 0.2.5
Summary: Simple site summary generator
Home-page: https://github.com/GaoangLiu/rss
Author: GaoangLiu
Author-email: GaoangLau@gmail.com
Classifier: Programming Language :: Python :: 3
Classifier: License :: OSI Approved :: MIT License
Classifier: Operating System :: OS Independent
Requires-Dist: codefast (>=0.6.3)
Requires-Dist: pydantic
Requires-Dist: dofast
Requires-Dist: schedule
Requires-Dist: authc
Requires-Dist: requests
Requires-Dist: redis
Requires-Dist: feedparser
Requires-Dist: simauth
Requires-Dist: pyshorteners
